pybar/__init__.py
pybar/configuration.yaml
pybar/dut_configuration_mio.yaml
pybar/dut_configuration_mmc3_16chip_multi_tx_eth.yaml
pybar/dut_configuration_mmc3_8chip_eth.yaml
pybar/dut_configuration_mmc3_8chip_multi_tx_eth.yaml
pybar/dut_mio.yaml
pybar/dut_mmc3_16chip_multi_tx_eth.yaml
pybar/dut_mmc3_8chip_eth.yaml
pybar/dut_mmc3_8chip_multi_tx_eth.yaml
pybar/fei4_run_base.py
pybar/online_monitor.py
pybar/run_manager.py
pybar/ViTablesPlugin/__init__.py
pybar/ViTablesPlugin/pybar_plugin.py
pybar/analysis/__init__.py
pybar/analysis/analysis.py
pybar/analysis/analysis_utils.py
pybar/analysis/analyze_raw_data.py
pybar/analysis/plotting/__init__.py
pybar/analysis/plotting/plotting.py
pybar/config/fei4/configs/std_cfg_fei4a.cfg
pybar/config/fei4/configs/std_cfg_fei4b.cfg
pybar/config/fei4/fdacs/fdac_std_cfg_fei4a.dat
pybar/config/fei4/fdacs/fdac_std_cfg_fei4b.dat
pybar/config/fei4/masks/c_high_std_cfg_fei4a.dat
pybar/config/fei4/masks/c_high_std_cfg_fei4b.dat
pybar/config/fei4/masks/c_low_std_cfg_fei4a.dat
pybar/config/fei4/masks/c_low_std_cfg_fei4b.dat
pybar/config/fei4/masks/enable_std_cfg_fei4a.dat
pybar/config/fei4/masks/enable_std_cfg_fei4b.dat
pybar/config/fei4/masks/enablediginj_std_cfg_fei4a.dat
pybar/config/fei4/masks/enablediginj_std_cfg_fei4b.dat
pybar/config/fei4/masks/imon_std_cfg_fei4a.dat
pybar/config/fei4/masks/imon_std_cfg_fei4b.dat
pybar/config/fei4/tdacs/tdac_std_cfg_fei4a.dat
pybar/config/fei4/tdacs/tdac_std_cfg_fei4b.dat
pybar/daq/__init__.py
pybar/daq/fei4_raw_data.py
pybar/daq/fei4_record.py
pybar/daq/fifo_readout.py
pybar/daq/readout_utils.py
pybar/fei4/__init__.py
pybar/fei4/fei4_defines.py
pybar/fei4/register.py
pybar/fei4/register_utils.py
pybar/firmware/mio.bit
pybar/firmware/mmc3_16chip_multi_tx_eth.bin
pybar/firmware/mmc3_16chip_multi_tx_eth.bit
pybar/firmware/mmc3_16chip_multi_tx_eth.mcs
pybar/firmware/mmc3_8chip_eth.bin
pybar/firmware/mmc3_8chip_eth.bit
pybar/firmware/mmc3_8chip_eth.mcs
pybar/firmware/mmc3_8chip_multi_tx_eth.bin
pyBAR-3.1.2.dist-info/LICENSE.txt
pyBAR-3.1.2.dist-info/METADATA
pyBAR-3.1.2.dist-info/WHEEL
pyBAR-3.1.2.dist-info/top_level.txt
pyBAR-3.1.2.dist-info/RECORD
