Metadata-Version: 2.1
Name: pyBAR
Version: 3.1.2
Summary: pyBAR - Bonn ATLAS Readout in Python
Home-page: https://github.com/SiLab-Bonn/pyBAR
Author: Jens Janssen, David-Leon Pohl
Author-email: janssen@physik.uni-bonn.de, pohl@physik.uni-bonn.de
Maintainer: Jens Janssen, David-Leon Pohl
Maintainer-email: janssen@physik.uni-bonn.de, pohl@physik.uni-bonn.de
License: BSD 3-Clause ("BSD New" or "BSD Simplified") License
Platform: any
Requires-Dist: basil-daq (<3.0.0,>=2.4.12)
Requires-Dist: pyBAR-fei4-interpreter (<1.4,>=1.3)
Requires-Dist: pixel-clusterizer (<3.2,>=3.1)
Requires-Dist: bitarray (>=0.8.1)
Requires-Dist: contextlib2
Requires-Dist: matplotlib
Requires-Dist: numpy
Requires-Dist: progressbar-latest (>=2.4)
Requires-Dist: tables
Requires-Dist: pyyaml
Requires-Dist: scipy
Requires-Dist: mock
Requires-Dist: nose
Requires-Dist: pyqtgraph (>=0.10)
Requires-Dist: pyserial
Requires-Dist: pyvisa
Requires-Dist: pyvisa-py
Requires-Dist: pyzmq
